ssam/__init__.py
ssam/classes.py
ssam/ssam.py
ssamwaste-1.0.1.dist-info/LICENSE
ssamwaste-1.0.1.dist-info/METADATA
ssamwaste-1.0.1.dist-info/WHEEL
ssamwaste-1.0.1.dist-info/top_level.txt
ssamwaste-1.0.1.dist-info/RECORD
