Metadata-Version: 2.1
Name: ssamwaste
Version: 1.0.1
Summary: A simple library for the SSAM Waste Schedule API written in Python 3.
Home-page: https://github.com/bitcanon/ssamwaste
Author: Mikael Schultz
Author-email: mikael@bitcanon.com
License: UNKNOWN
Platform: UNKNOWN
Classifier: Programming Language :: Python :: 3
Classifier: License :: OSI Approved :: MIT License
Classifier: Operating System :: OS Independent
Requires-Python: >=3.6
Requires-Dist: requests
